[
   {
      "homeTeam":{
         "name":"BEKK",
         "goals":2,
         "links":{
            "team":"http://..."
         }
      },
      "awayTeam":{
         "name":"FC Fritidsklubben",
         "goals":3,
         "links":{
            "team":"http://..."
         }
      },
      "arena":{
         "name":"Linderud",
         "mapUrl":"https://goo.gl/maps/bhHpsA7wbK92"
      },
      "startTime":"2015-09-29T18:40:00.000Z",
      "links":{
         "details":"/match/123"
      }
   },
   {
      "homeTeam":{
         "name":"NRK",
         "goals":0,
         "links":{
            "team":"http://..."
         }
      },
      "awayTeam":{
         "name":"BEKK",
         "goals":11,
         "links":{
            "team":"http://..."
         }
      },
      "arena":{
         "name":"Manglerudhallen",
         "mapUrl":"https://goo.gl/maps/bhHpsA7wbK92"
      },
      "startTime":"2015-09-23T19:30:00.000Z",
      "links":{
         "match":"/match/123"
      }
   },
   {
      "homeTeam":{
         "name":"Ciber",
         "goals":2,
         "links":{
            "team":"http://..."
         }
      },
      "awayTeam":{
         "name":"BEKK",
         "goals":2,
         "links":{
            "team":"http://..."
         }
      },
      "arena":{
         "name":"Voldsløkka, B",
         "mapUrl":"https://goo.gl/maps/bhHpsA7wbK92"
      },
      "startTime":"2015-08-31T17:30:00.000Z",
      "links":{
         "match":"/match/123"
      }
   }
]
